getmyfile.py
getmyfile-0.1.1.dist-info/LICENSE
getmyfile-0.1.1.dist-info/METADATA
getmyfile-0.1.1.dist-info/WHEEL
getmyfile-0.1.1.dist-info/entry_points.txt
getmyfile-0.1.1.dist-info/RECORD
